ftrack_action_handler/__init__.py
ftrack_action_handler/_version.py
ftrack_action_handler/action/__init__.py
ftrack_action_handler/action/advanced.py
ftrack_action_handler/action/base.py
ftrack_action_handler-0.3.1.dist-info/LICENSE.txt
ftrack_action_handler-0.3.1.dist-info/METADATA
ftrack_action_handler-0.3.1.dist-info/WHEEL
ftrack_action_handler-0.3.1.dist-info/top_level.txt
ftrack_action_handler-0.3.1.dist-info/RECORD
