Metadata-Version: 2.1
Name: ftrack-action-handler
Version: 0.3.1
Summary: Base Class for handling ftrack actions.
Author-email: ftrack <support@ftrack.com>
License: Apache License
Project-URL: Homepage, https://github.com/ftrackhq/ftrack-action-handler
Project-URL: Source, https://github.com/ftrackhq/ftrack-action-handler.git
Keywords: ftrack
Classifier: Intended Audience :: Developers
Classifier: License :: OSI Approved :: Apache Software License
Classifier: Programming Language :: Python :: 2
Classifier: Programming Language :: Python :: 3
Requires-Python: <4.0,>=2.7.9
License-File: LICENSE.txt
Requires-Dist: ftrack-python-api <4,>=2
Requires-Dist: future <1,>=0.16.0
Provides-Extra: docs
Requires-Dist: sphinx ; extra == 'docs'
Requires-Dist: sphinx-pyproject ; extra == 'docs'
Requires-Dist: sphinx-rtd-theme ; extra == 'docs'
Requires-Dist: lowdown ; extra == 'docs'
